pysga/__init__.py
pysga/configure.py
pysga/family.py
pysga/fobj_function.py
pysga/searchgroupalgorithm.kv
pysga/sga.py
pysga/sgaApp.py
pysga/tournament.py
pysga-1.2.7.dist-info/DESCRIPTION.rst
pysga-1.2.7.dist-info/METADATA
pysga-1.2.7.dist-info/RECORD
pysga-1.2.7.dist-info/WHEEL
pysga-1.2.7.dist-info/metadata.json
pysga-1.2.7.dist-info/top_level.txt
